docs/source/conf.py
typon/__init__.py
typon/include/.clang-format
typon/include/.clang-tidy
typon/include/python/basedef.hpp
typon/include/python/builtins.hpp
typon/include/python/dataclasses.hpp
typon/include/python/hashlib.hpp
typon/include/python/io.hpp
typon/include/python/json.hpp
typon/include/python/os.hpp
typon/include/python/referencemodel.hpp
typon/include/python/socket.hpp
typon/include/python/stat.hpp
typon/include/python/sys.hpp
typon/include/python/time.hpp
typon/include/python/typon.hpp
typon/include/python/builtins/bool.hpp
typon/include/python/builtins/bytes.hpp
typon/include/python/builtins/complex.hpp
typon/include/python/builtins/dict.hpp
typon/include/python/builtins/exception.hpp
typon/include/python/builtins/int.hpp
typon/include/python/builtins/list.hpp
typon/include/python/builtins/mutex.hpp
typon/include/python/builtins/print.hpp
typon/include/python/builtins/range.hpp
typon/include/python/builtins/set.hpp
typon/include/python/builtins/slice.hpp
typon/include/python/builtins/str.hpp
typon/runtime/.clang-format
typon/runtime/.clang-tidy
typon/runtime/.git
typon/runtime/.gitignore
typon/runtime/README.md
typon/runtime/rt/examples/.gitignore
typon/runtime/rt/examples/Makefile
typon/runtime/rt/examples/Makefile.clang++-14
typon/runtime/rt/examples/Makefile.g++-11
typon/runtime/rt/examples/await_ready.cpp
typon/runtime/rt/examples/await_result.cpp
typon/runtime/rt/examples/cat.cpp
typon/runtime/rt/examples/fork.cpp
typon/runtime/rt/examples/fork_exceptions.cpp
typon/runtime/rt/examples/fork_variations.cpp
typon/runtime/rt/examples/future_awaited.cpp
typon/runtime/rt/examples/future_detached.cpp
typon/runtime/rt/examples/loop.cpp
typon/runtime/rt/examples/mutex.cpp
typon/runtime/rt/examples/naive_fibonacci_accelerated_fork.cpp
typon/runtime/rt/examples/naive_fibonacci_baseline.cpp
typon/runtime/rt/examples/naive_fibonacci_fork.cpp
typon/runtime/rt/examples/naive_fibonacci_fork_into.cpp
typon/runtime/rt/examples/naive_fibonacci_fork_void.cpp
typon-0.3.dist-info/METADATA
typon-0.3.dist-info/WHEEL
typon-0.3.dist-info/entry_points.txt
typon-0.3.dist-info/top_level.txt
typon-0.3.dist-info/RECORD
