Metadata-Version: 2.1
Name: typon
Version: 0.3
Summary: A Python-to-C++ compiler geared towards concurrency
Author-email: Xavier Thompson <xavier.thompson@nexedi.com>, Tom Niget <tom.niget@nexedi.com>
Project-URL: Homepage, https://typon.nexedi.com
Project-URL: Repository, https://lab.nexedi.com/typon/typon-compiler
Requires-Python: >=3.12
Requires-Dist: clang-format ~=18.1.3
Requires-Dist: colorama ~=0.4.6
Requires-Dist: colorful ~=0.6.0a1
Requires-Dist: nanobind ~=1.9.2
Requires-Dist: numpy ~=2.0.0rc1
Requires-Dist: pybind11 ~=2.12.0
Requires-Dist: Pygments ~=2.17.2
Requires-Dist: python-dotenv ~=1.0.1
Provides-Extra: test
Requires-Dist: numpy ~=1.25.1 ; extra == 'test'
